Metadata-Version: 2.1
Name: shap-legacy
Version: 0.36.0
Summary: A unified approach to explain the output of any machine learning model.
Home-page: http://github.com/slundberg/shap
Author: Scott Lundberg
Author-email: slund1@cs.washington.edu
License: MIT
Platform: UNKNOWN
Classifier: Programming Language :: Python :: 3
Classifier: Programming Language :: Python :: 3.6
Requires-Dist: numpy
Requires-Dist: scipy
Requires-Dist: scikit-learn
Requires-Dist: pandas
Requires-Dist: tqdm (>4.25.0)
Requires-Dist: slicer
Requires-Dist: numba
Provides-Extra: all
Requires-Dist: ipython ; extra == 'all'
Requires-Dist: lime ; extra == 'all'
Requires-Dist: matplotlib ; extra == 'all'
Provides-Extra: others
Requires-Dist: lime ; extra == 'others'
Provides-Extra: plots
Requires-Dist: matplotlib ; extra == 'plots'
Requires-Dist: ipython ; extra == 'plots'
